grrargparse/__init__.py
grrargparse/_grrargparse_helpers.py
grrargparse/_grrargparser.py
grrargparse/_module.py
grrargparse/grr_logging.py
grrargparse-0.4.1.dist-info/DESCRIPTION.rst
grrargparse-0.4.1.dist-info/METADATA
grrargparse-0.4.1.dist-info/RECORD
grrargparse-0.4.1.dist-info/WHEEL
grrargparse-0.4.1.dist-info/metadata.json
grrargparse-0.4.1.dist-info/top_level.txt
