Metadata-Version: 2.0
Name: grrargparse
Version: 0.4.1
Summary: A Modular base for command line applications
Home-page: https://github.com/shiftbreak/grrargparse
Author: shiftbreak
Author-email: shiftbreak.code@gmail.com
License: MIT
Keywords: argparse interactive modulular
Platform: UNKNOWN
Classifier: Development Status :: 4 - Beta
Classifier: Programming Language :: Python :: 3
